microrequests/__init__.py
microrequests-0.1.2.dist-info/LICENSE.txt
microrequests-0.1.2.dist-info/METADATA
microrequests-0.1.2.dist-info/WHEEL
microrequests-0.1.2.dist-info/top_level.txt
microrequests-0.1.2.dist-info/RECORD
