Metadata-Version: 2.1
Name: microrequests
Version: 0.1.2
Summary: microrequests is a wrapper over requests module - makes it more efficient to consume microservices in Python
Home-page: http://www.abhinav.co/microrequests.html
Author: Abhinav Saxena
Author-email: abhinav061@gmail.com
License: UNKNOWN
Platform: UNKNOWN
Requires-Dist: requests
